django_sso/__init__.py
django_sso/exceptions.py
django_sso/gate/__init__.py
django_sso/gate/admin.py
django_sso/gate/apps.py
django_sso/gate/forms.py
django_sso/gate/models.py
django_sso/gate/tests.py
django_sso/gate/urls.py
django_sso/gate/views.py
django_sso/gate/migrations/0001_initial.py
django_sso/gate/migrations/0002_alter_service_token.py
django_sso/gate/migrations/0003_authenticationrequest_next_url.py
django_sso/gate/migrations/0004_authenticationrequest_authenticated.py
django_sso/gate/migrations/__init__.py
django_sso/service/__init__.py
django_sso/service/admin.py
django_sso/service/apps.py
django_sso/service/models.py
django_sso/service/urls.py
django_sso/service/views.py
django_sso/service/migrations/__init__.py
django_sso-1.0.0.dist-info/METADATA
django_sso-1.0.0.dist-info/WHEEL
django_sso-1.0.0.dist-info/top_level.txt
django_sso-1.0.0.dist-info/RECORD
