Metadata-Version: 2.1
Name: django-sso
Version: 1.0.0
Summary: UNKNOWN
Home-page: https://github.com/davidhaker/django-sso
Author: DAVIDhaker
Author-email: me@davidhaker.ru
License: UNKNOWN
Keywords: Django SSO Single Sign-On
Platform: UNKNOWN
Requires-Dist: django
